qrainbowstyle/__init__.py
qrainbowstyle/__main__.py
qrainbowstyle/colorsystem.py
qrainbowstyle/palette.py
qrainbowstyle/extras/__init__.py
qrainbowstyle/extras/debugging.py
qrainbowstyle/styles/__init__.py
qrainbowstyle/styles/DarkOrange/__init__.py
qrainbowstyle/styles/DarkOrange/style_rc.py
qrainbowstyle/styles/LightOrange/__init__.py
qrainbowstyle/styles/LightOrange/style_rc.py
qrainbowstyle/styles/Oceanic/__init__.py
qrainbowstyle/styles/Oceanic/style_rc.py
qrainbowstyle/styles/QDarkStyle/__init__.py
qrainbowstyle/styles/QDarkStyle/style_rc.py
qrainbowstyle/styles/QDarkStyle3/__init__.py
qrainbowstyle/styles/QDarkStyle3/style_rc.py
qrainbowstyle/styles/QDarkStyle3Light/__init__.py
qrainbowstyle/styles/QDarkStyle3Light/style_rc.py
qrainbowstyle/utils/__init__.py
qrainbowstyle/utils/__utils.py
qrainbowstyle/utils/images.py
qrainbowstyle/utils/scss.py
qrainbowstyle/widgets/__init__.py
qrainbowstyle/widgets/GoogleMapsWidget/GoogleMapsHtml.py
qrainbowstyle/widgets/GoogleMapsWidget/MapsWidget.py
qrainbowstyle/widgets/GoogleMapsWidget/OpenStreetMapsHtml.py
qrainbowstyle/widgets/GoogleMapsWidget/__init__.py
qrainbowstyle/widgets/PythonQtWidgets/__init__.py
qrainbowstyle/widgets/PythonQtWidgets/picker.py
qrainbowstyle/widgets/QRoundProgressBar/__init__.py
qrainbowstyle/widgets/QRoundProgressBar/qroundprogressbar.py
qrainbowstyle/widgets/QtWaitingSpinner/__init__.py
qrainbowstyle/widgets/QtWaitingSpinner/designer.py
qrainbowstyle/widgets/QtWaitingSpinner/pyqtspinner.py
qrainbowstyle/windows/FramelessMessageBox.py
qrainbowstyle/windows/FramelessWindow.py
qrainbowstyle/windows/FramelessWindowWin.py
qrainbowstyle/windows/__init__.py
qrainbowstyle/windows/base/Buttons.py
qrainbowstyle/windows/base/Titlebar.py
qrainbowstyle/windows/base/Window.py
qrainbowstyle/windows/base/__init__.py
qrainbowstyle-0.9.6.dist-info/AUTHORS.rst
qrainbowstyle-0.9.6.dist-info/LICENSE.rst
qrainbowstyle-0.9.6.dist-info/METADATA
qrainbowstyle-0.9.6.dist-info/WHEEL
qrainbowstyle-0.9.6.dist-info/entry_points.txt
qrainbowstyle-0.9.6.dist-info/top_level.txt
qrainbowstyle-0.9.6.dist-info/RECORD
