Metadata-Version: 2.1
Name: qrainbowstyle
Version: 0.9.6
Summary: The most complete customizable stylesheet for Python and Qt applications
Home-page: https://github.com/desty2k/QRainbowStyleSheet
Author: Wojciech Wentland
Author-email: wojciech.wentland@int.pl
License: MIT
Project-URL: Issues, https://github.com/desty2k/QRainbowStyleSheet/issues
Project-URL: Docs, https://desty2k.github.io/QRainbowStyleSheet/
Platform: UNKNOWN
Classifier: Development Status :: 5 - Production/Stable
Classifier: Environment :: X11 Applications :: Qt
Classifier: Environment :: Win32 (MS Windows)
Classifier: Intended Audience :: Developers
Classifier: License :: OSI Approved :: MIT License
Classifier: Operating System :: Microsoft :: Windows
Classifier: Operating System :: POSIX :: Linux
Classifier: Operating System :: MacOS
Classifier: Programming Language :: Python :: 3.5
Classifier: Programming Language :: Python :: 3.6
Classifier: Programming Language :: Python :: 3.7
Classifier: Programming Language :: Python :: 3.8
Classifier: Programming Language :: Python :: 3.9
Classifier: Topic :: Software Development :: Libraries :: Application Frameworks
Requires-Python: >=3.5
License-File: LICENSE.rst
License-File: AUTHORS.rst
Requires-Dist: helpdev (>=0.6.10)
Requires-Dist: qtpy (>=1.9)
Requires-Dist: PyQtWebEngine
Provides-Extra: develop
Requires-Dist: qtsass ; extra == 'develop'
Requires-Dist: watchdog ; extra == 'develop'
Provides-Extra: docs
Requires-Dist: sphinx ; extra == 'docs'
Requires-Dist: sphinx-rtd-theme ; extra == 'docs'
Provides-Extra: example
Requires-Dist: pyqt5 ; extra == 'example'
Requires-Dist: pyside2 ; extra == 'example'
